rolling_checksum_mod.py
rolling_checksum_py_mod.py
setup.py
rolling_checksum_py_mod.egg-info/PKG-INFO
rolling_checksum_py_mod.egg-info/SOURCES.txt
rolling_checksum_py_mod.egg-info/dependency_links.txt
rolling_checksum_py_mod.egg-info/top_level.txt