Metadata-Version: 1.1
Name: rolling-checksum-py-mod
Version: 1.0.1
Summary: Pure Python module providing a variable-length, content-based blocking algorithm
Home-page: http://stromberg.dnsalias.org/~dstromberg/rolling_checksum_mod/
Author: Daniel Richard Stromberg
Author-email: strombrg@gmail.com
License: GPLv3
Platform: Cross platform
Classifier: Development Status :: 5 - Production/Stable
Classifier: Intended Audience :: Developers
Classifier: Programming Language :: Python :: 3
